draw_nn/__init__.py
draw_nn/draw_nn.py
draw_nn-0.1.dist-info/METADATA
draw_nn-0.1.dist-info/WHEEL
draw_nn-0.1.dist-info/top_level.txt
draw_nn-0.1.dist-info/RECORD
